mcp_telegram/__init__.py
mcp_telegram/py.typed
mcp_telegram/server.py
mcp_telegram/telegram.py
mcp_telegram/tools.py
mseep_mcp_telegram-0.1.6.dist-info/licenses/LICENSE
mseep_mcp_telegram-0.1.6.dist-info/METADATA
mseep_mcp_telegram-0.1.6.dist-info/WHEEL
mseep_mcp_telegram-0.1.6.dist-info/entry_points.txt
mseep_mcp_telegram-0.1.6.dist-info/top_level.txt
mseep_mcp_telegram-0.1.6.dist-info/RECORD
