Metadata-Version: 2.4
Name: mseep-mcp-telegram
Version: 0.1.6
Summary: MCP server to work with Telegram through MTProto
Author-email: mseep <support@skydeck.ai>
Requires-Python: >=3.11
License-File: LICENSE
Requires-Dist: mcp>=1.1.0
Requires-Dist: telethon>=1.23.0
Requires-Dist: pydantic>=2.0.0
Requires-Dist: pydantic-settings>=2.6.0
Requires-Dist: typer>=0.15.0
Requires-Dist: xdg-base-dirs>=6.0.0
Dynamic: license-file
